[
  {
    "symbol": "TLM/USDT",
    "action": "下架",
    "type": "合约",
    "time": "2025-08-26",
    "exchange": "blofin"
  },
  {
    "symbol": "COS/USDT",
    "action": "下架",
    "type": "合约",
    "time": "2025-08-26",
    "exchange": "blofin"
  },
  {
    "symbol": "1000XEC/USDT",
    "action": "下架",
    "type": "合约",
    "time": "2025-08-26",
    "exchange": "blofin"
  },
  {
    "symbol": "1000BTT/USDT",
    "action": "下架",
    "type": "合约",
    "time": "2025-08-26",
    "exchange": "blofin"
  }
]